Calcolatrice/accumulatore.vhd
library IEEE;
use IEEE.STD_LOGIC_1164.ALL;
-- Uncomment the following library declaration if using
-- arithmetic functions with Signed or Unsigned values
use IEEE.NUMERIC_STD.ALL;
-- Uncomment the following library declaration if instantiating
-- any Xilinx leaf cells in this code.
--library UNISIM;
--use UNISIM.VComponents.all;

entity accumulator is
	Port (clk, up, left, right, center : in std_logic;
	result: in signed(31 downto 0);
	acc: out signed(31 downto 0)
	);
end accumulator;

architecture Behavioral of accumulator is
begin
--result<="00000000000000000000000000000000"; --Per reset iniziale
	process(clk, center) is
		begin
		if center='1' then
		acc<=(others=>'0');
		elsif rising_edge(clk) and (up='1' or left='1' or right='1') then
		acc<=result;
		end if;
	end process;
end Behavioral;

alu.vhd
library IEEE;
use IEEE.STD_LOGIC_1164.ALL;
-- Uncomment the following library declaration if using
-- arithmetic functions with Signed or Unsigned values
use IEEE.NUMERIC_STD.ALL;
-- Uncomment the following library declaration if instantiating
-- any Xilinx leaf cells in this code.
--library UNISIM:
--use UNISIM.VComponents.all;

entity alu is
Port (number: in signed(31 downto 0);
	up, left, right: in std_logic;
	acc: in signed(31 downto 0);
	result: out signed(31 downto 0)
	);
end alu;

architecture Behavioral of alu is
	signal mult: signed(63 downto 0);
begin
	process(up, left, right) begin
		--result<=number; --Inizialmente 11 risultato é indeterminato,
		--ma così non vengono effettuate operazioni non necessarie
		if(up='1') then result<=(number+acc); end if;
		if(left='1') then result<=(acc-number); end if;
		if(right='1') then result<=mult(31 downto 0); end if;
	end process;
	mult<=acc*number;

end Behavioral;

Calcolatrice/driver.vhd
library IEEE;
use IEEE.STD_LOGIC_1164.ALL;
-- Uncomment the following library declaration if using
-- arithmetic functions with Signed or Unsigned values
use IEEE.NUMERIC_STD.ALL;
-- Uncomment the following library declaration if instantiating
-- any Xilinx leaf cells in this code.
--library UNISIM;
-- use UNISIM.VComponents.all;

entity driver is generic (
		size : integer := 20
	);
	Port (
		clk : in std_logic;
		reset : in std_logic;
		digit0 : in std_logic_vector( 3 downto 0 );
		digitl : in std_logic_vector( 3 downto 0 );
		digit2 : in std_logic_vector( 3 downto 0 );
		digit3 : in std_logic_vector( 3 downto 0 );
		digit4 : in std_logic_vector( 3 downto 0 );
		digit5 : in std_logic_vector( 3 downto 0 );
		digit6 : in std_logic_vector( 3 downto 0 );
		digit7 : in std_logic_vector( 3 downto 0 );
		CA, CB, CC, CD, CE, CF, CG, DP : out std_logic;
		AN : out std_logic_vector( 7 downto 0 )
	);
end driver;

architecture Behavioral of driver is
-- We will use a counter to derive the frequency for the displays
-- Clock is 100 MHz, we use 3 bits to address the display, so count every
-- size - 3 bits.
signal flick_counter : unsigned( 19 downto 0 ); --20bit, da 19 a 0.
-- The digit is temporarily stored here
signal digit : std_logic_vector( 3 downto 0);
-- Collect the values of the cathodes here
signal cathodes : std_logic_vector( 7 downto 0 );

begin

	-- Divide the clock
	process ( clk, reset ) begin
		if reset = '0' then
			flick_counter <= ( others => '0' );
		elsif rising_edge( clk ) then
			flick_counter <= flick_counter + 1;
		end if;
	end process;
	-- Select the anods: decoder 3-3
	with flick_counter(19 downto 17) select
	AN <=
	"11111110" when "000",
	"11111101" when "001",
	"11111011" when "010",
	"11110111" when "011",
	"11101111" when "100",
	"11011111" when "101",
	"10111111" when "110",
	"01111111" when others;
	-- Select the digit: multiplexer 8-1
	with flick_counter(19 downto 17) select
	digit <=
	digit0 when "000",
	digitl when "001",
	digit2 when "010",
	digit3 when "011",
	digit4 when "100",
	digit5 when "101",
	digit6 when "110",
	digit7 when others;

	-- Decode the digit 7-segment display decoder
	with digit select
	cathodes <=
	-- DP, CG, CF, CE, CD, CC, CB, CA
	"11000000" when "0000",
	"11111001" when "0001",
	"10100100" when "0010",
	"10110000" when "0011",
	"10011001" when "0100",
	"10010010" when "0101",
	"10000010" when "0110",
	"11111000" when "0111",
	"10000000" when "1000",
	"10010000" when "1001",
	"10001000" when "1010",
	"10000011" when "1011",
	"11000110" when "1100",
	"10100001" when "1101",
	"10000110" when "1110",
	"10001110" when others;

	DP <= cathodes( 7 );
	CG <= Cathodes( 6 );
	CF <= cathodes( 5 );
	CE <= cathodes( 4 );
	CD <= cathodes( 3 );
	CC <= cathodes( 2 );
	CB <= cathodes( 1 );
	CA <= cathodes( 0 );

end Behavioral;

Calcolatrice/edge_detector.vhd
library IEEE;
use IEEE.STD_LOGIC_1164.ALL;
-- Uncomment the following library declaration if using
-- arithmetic functions with Signed or Unsigned values
-- use IEEE.NUMERIC_STD.ALL;
-- Uncomment the following library declaration if instantiating
-- any Xilinx leaf cells in this code.
--library UNISIM;
--use UNISIM.VComponents.all;

entity edge_detector is
Port (clk, res, btn : in std_logic;
	edge : out std_logic
);
end edge_detector;

architecture Behavioral of edge_detector is
	type stato is (at_zero, at_edge, at_one);
	signal present_state, next_state : stato;
	begin

	seq: process(res, clk) is
	begin
		if res='1' then
		present_state<=at_zero;
		elsif rising edge(clk) then
		present_state<=next_state;
		end if;
	end process seq;

	futuro: process(present_state, btn) is
	begin
		case present_state is
		when at_zero=>
		if btn='0' then
		next_state<=at_zero;
		else
		next_state<=at_edge;
		end if;
		
		when at_edge=>
		if btn='0' then
		next_state<=at_zero;
		else
		next_state<=at_one;
		end if;
		
		when at_one=>
		if btn='0' then
		next_state<=at_zero;
		else
		next_state<=at_one;
		end if;
		end case;
	end process futuro;

	uscite: process(present_state) is
	begin
		edge<='0';
		if present_state=at_edge then
		edge<='1';
		end if;
	end process uscite;

end Behavioral;

Calcolatrice/TopLevel.vhd
library IEEE;
use IEEE.STD_LOGIC_1164.ALL;
-- Uncomment the following library declaration if using
-- arithmetic functions with Signed or Unsigned values
use IEEE.NUMERIC_STD.ALL;
-- Uncomment the following library declaration if instantiating
-- any Xilinx leaf cells in this code.
--library UNISIM;
--use UNISIM.VComponents.all;

entity Calcolatrice is
Port (clk, res: in std_logic;
		SW: in std_logic_vector(15 downto 0);
		led: out std_logic_vector(15 downto 0);
		CA, CB, CC, CD, CE, CF, CG, DP: out std_logic;
		AN: out std_logic_vector (7 downto 0);
		BTNC, BTNU, BTNL, BTNR, BTND : in std_logic;
		output: out std_logic_vector(31 downto 0)
	);

end Calcolatrice;

architecture Behavioral of Calcolatrice is

	signal center_edge, up_edge , left_edge , right_edge, down_edge : std_logic;
	signal acc_in, acc_out : signed(31 downto 0);
	-- signal acc_init, acc enable: std logic;
	signal do_add , do_sub , do_mult : std_logic;
	signal display_value : std_logic_vector(31 downto 0);
	signal sw_input : std_logic_vector(31 downto 0);

begin

	center_detect : entity work.edge_detector(Behavioral)
	port map(
		clk => clk,
		btn => BTNC,
		edge => center_edge,
		res => res
	);
	
	up_detect : entity work.edge_detector(Behavioral)
	port map(
		clk => clk,
		btn => BTNU,
		edge => up_edge,
		res => res
	);
	
	down_detect : entity work.edge_detector(Behavioral)
	port map(
		clk => clk,
		btn => BTND,
		edge => down_edge,
		res => res
	);
	
	left_detect : entity work.edge_detector(Behavioral)
	port map(
		clk => clk,
		btn => BTNL,
		edge => left_edge,
		res => res
	);
	
	right_detect : entity work.edge_detector(Behavioral)
	port map(
		clk => clk,
		btn => BTNR,
		edge => right_edge,
		res => res
	);

	thedriver : entity work.driver(behavioral)

	generic map(
		size => 21

	) port map(
		clk => clk,
		reset => res,
		digit0 => display_value(3 downto 0),
		digitl => display_value(7 downto 4),
		digit2 => display_value(11 downto 8),
		digit3 => display_value(15 downto 12),
		digit4 => display_value(19 downto 16),
		digit5 => display_value(23 downto 20),
		digit6 => display_value(27 downto 24),
		digit7 => display_value(31 downto 28),
		CA => CA,
		CB => CB,
		CC => CC,
		CD => CD,
		CE => CE,
		CF => CF,
		CG => CG,
		DP => DP,
		AN => AN
	);

	LED <= SW;

	sw_input <= SW(15) & SW(15) & SW(15) & SW(15) & SW(15) & SW(15) & SW(15) & SW(15) & SW(15)
	& SW(15) & SW(15) & SW(15) & SW(15) & SW(15) & SW(15) & SW(15) & SW;

	the_alu : entity work.alu(Behavioral) port map (
		acc => acc_out,
		number => signed(sw_input),
		up => do_add,
		left => do_sub,
		right => do_mult,
		result => acc_in
	);
	do_add <= up_edge;
	do_sub <= left_edge;
	do_mult <= right_edge;

	the_accumulator : entity work.accumulator(Behavioral)
	port map(
		clk => clk,
		center => center_edge,
		up => up_edge,
		left => left_edge,
		right => right_edge,
		result => acc_in,
		acc => acc_out
	);
	display_value <= std_logic_vector(acc_out);
	output <= std_logic_vector(acc_out);
	--acc_enable <= up_edge or left_edge or right _edge or down_edge;
	--acc_init <= center_edge;
	
end Behavioral;

Calcolatrice/TopLevelTestBench.vhd
library IEEE;
use IEEE.STD_LOGIC_1164.ALL;
-- Uncomment the following library declaration if using
-- arithmetic functions with Signed or Unsigned values
use IEEE.NUMERIC_STD.ALL;
-- Uncomment the following library declaration if instantiating
-- any Xilinx leaf cells in this code.
--library UNISIM;
--use UNISIM.VComponents.all;

entity Calcolatrice_testbench is
-- Port ( );
end Calcolatrice_testbench;

architecture Behavioral of Calcolatrice_testbench is

component Calcolatrice
	Port (clk, res: in std_logic;
		SW: in std_logic_vector(15 downto 0);
		led: out std_logic_vector(15 downto 0);
		CA, CB, CC, CD, CE, CF, CG, DP : out std_logic;
		AN: out std_logic_vector (7 downto 0);
		BTNC, BTNU, BTNL, BTNR, BTND : in std_logic;
		output: out std_logic_vector(31 downto 0)
	);
end component;
signal clk, res, CA, CB, CC, CD, CE, CG, CF, DP, BTNC, BTNU, BTNL, BTNR, BTND : std_logic:='0';
signal SW, led : std_logic_vector(15 downto 0);
signal AN : std_logic_vector (7 downto 0);
signal output: std_logic_vector (31 downto 0);

begin
uut: Calcolatrice
	port map(
	clk => clk,
	res => res,
	SW => SW,
	led => led,
	CA => CA,
	CB => CB,
	CC => CC,
	CD => CD,
	CE => CE,
	CF => CF,
	CG => CG,
	DP => DP,
	AN => AN,
	BTNC => BTNC,
	BTNU => BTNU,
	BTNL => BTNL,
	BTNR => BTNR,
	BTND => BTND,
	output => output
	);

clock : process begin clk<='1'; wait for 5 ns; clk<= not clk; wait for 5 ns; end process;

ciclo : process begin
	SW<="0000000000100100" ;--Impostiamo in input il mmero 36 sugli switch
	BTNC <='1';
	wait for 10 ns;
	BTNC <='0';
	wait for 100 ns;
	--Somma 1
	BTNU <='1';
	wait for 10 ns;
	BTNU <='0';
	wait for 100 ns;
	--Somma 2
	SW<="0000000000000100";      --Imposto in input il numero 4 sugli switch
	BTNU <='1';
	wait for 10 ns;
	BTNU <='0';
	wait for 100 ns; 		--Devo ottenere 40 in output
	--Sottrazione
	SW<="0000000000011110";      --Imposto in input il numero 30 sugli switch
	BTNL <='1';
	wait for 10 ns;
	BTNL <='0';
	wait for 100 ns; 		--Devo ottenere 10 in output
	--Moltiplicazione
	SW<="0000000000001010";      --Imposto in input il numero 10 sugli switch
	BTNR <='1';
	wait for 10 ns;
	BTNR <='0';
	wait for 100 ns; 		--Devo ottenere 100 in output
	--Reset
	BTNC <='1';
	wait for 10 ns;
	BTNC <='0';			--Devo ottenere 0 in output
	wait;

end process;
end Behavioral;

Calcolatrice/simulazione.vcd
$date
  Tue Jun 21 22:24:38 2022
$end
$version
  GHDL v0
$end
$timescale
  1 fs
$end
$scope module standard $end
$upscope $end
$scope module std_logic_1164 $end
$upscope $end
$scope module numeric_std $end
$upscope $end
$scope module calcolatrice_testbench $end
$var reg 1 ! clk $end
$var reg 1 " res $end
$var reg 1 # ca $end
$var reg 1 $ cb $end
$var reg 1 % cc $end
$var reg 1 & cd $end
$var reg 1 ' ce $end
$var reg 1 ( cg $end
$var reg 1 ) cf $end
$var reg 1 * dp $end
$var reg 1 + btnc $end
$var reg 1 , btnu $end
$var reg 1 - btnl $end
$var reg 1 . btnr $end
$var reg 1 / btnd $end
$var reg 16 0 sw[15:0] $end
$var reg 16 1 led[15:0] $end
$var reg 8 2 an[7:0] $end
$var reg 32 3 output[31:0] $end
$scope module uut $end
$upscope $end
$upscope $end
$enddefinitions $end
#0
1!
0"
U#
U$
U%
U&
U'
U(
U)
U*
1+
0,
0-
0.
0/
b0000000000100100 0
bUUUUUUUUUUUUUUUU 1
bUUUUUUUU 2
bUUUUUUUUUUUUUUUUUUUUUUUUUUUUUUUU 3
#5000000
0!
#10000000
1!
0+
#15000000
0!
#20000000
1!
#25000000
0!
#30000000
1!
#35000000
0!
#40000000
1!
#45000000
0!
#50000000
1!
#55000000
0!
#60000000
1!
#65000000
0!
#70000000
1!
#75000000
0!
#80000000
1!
#85000000
0!
#90000000
1!
#95000000
0!
#100000000
1!
#105000000
0!
#110000000
1!
1,
#115000000
0!
#120000000
1!
0,
#125000000
0!
#130000000
1!
#135000000
0!
#140000000
1!
#145000000
0!
#150000000
1!
#155000000
0!
#160000000
1!
#165000000
0!
#170000000
1!
#175000000
0!
#180000000
1!
#185000000
0!
#190000000
1!
#195000000
0!
#200000000
1!
#205000000
0!
#210000000
1!
#215000000
0!
#220000000
1!
1,
b0000000000000100 0
#225000000
0!
#230000000
1!
0,
#235000000
0!
#240000000
1!
#245000000
0!
#250000000
1!
#255000000
0!
#260000000
1!
#265000000
0!
#270000000
1!
#275000000
0!
#280000000
1!
#285000000
0!
#290000000
1!
#295000000
0!
#300000000
1!
#305000000
0!
#310000000
1!
#315000000
0!
#320000000
1!
#325000000
0!
#330000000
1!
1-
b0000000000011110 0
#335000000
0!
#340000000
1!
0-
#345000000
0!
#350000000
1!
#355000000
0!
#360000000
1!
#365000000
0!
#370000000
1!
#375000000
0!
#380000000
1!
#385000000
0!
#390000000
1!
#395000000
0!
#400000000
1!
#405000000
0!
#410000000
1!
#415000000
0!
#420000000
1!
#425000000
0!
#430000000
1!
#435000000
0!
#440000000
1!
1.
b0000000000001010 0
#445000000
0!
#450000000
1!
0.
#455000000
0!
#460000000
1!
#465000000
0!
#470000000
1!
#475000000
0!
#480000000
1!
#485000000
0!
#490000000
1!
#495000000
0!
#500000000
1!
#505000000
0!
#510000000
1!
#515000000
0!
#520000000
1!
#525000000
0!
#530000000
1!
#535000000
0!
#540000000
1!
#545000000
0!
#550000000
1!
1+
#555000000
0!
#560000000
1!
0+
